opentorsion/__init__.py
opentorsion/assembly.py
opentorsion/errors.py
opentorsion/excitation.py
opentorsion/parser.py
opentorsion/plots.py
opentorsion/utils.py
opentorsion/elements/__init__.py
opentorsion/elements/disk_element.py
opentorsion/elements/elastic_gear_element.py
opentorsion/elements/gear_element.py
opentorsion/elements/shaft_element.py
opentorsion/tests/__init__.py
opentorsion/tests/tests.py
opentorsion-0.3.0.dist-info/licenses/LICENSE
opentorsion-0.3.0.dist-info/METADATA
opentorsion-0.3.0.dist-info/WHEEL
opentorsion-0.3.0.dist-info/top_level.txt
opentorsion-0.3.0.dist-info/RECORD
