Metadata-Version: 2.4
Name: opentorsion
Version: 0.3.0
Summary: Open source library for creating torsional finite element models
Home-page: https://github.com/Aalto-Arotor/openTorsion
Author: Aalto ARotor
Author-email: arotor.software@aalto.fi
Project-URL: Bug Tracker, https://github.com/Aalto-Arotor/openTorsion/issues
Classifier: Programming Language :: Python :: 3
Classifier: License :: OSI Approved :: MIT License
Classifier: Operating System :: OS Independent
Requires-Python: >=3.11
License-File: LICENSE
Requires-Dist: matplotlib
Requires-Dist: numpy
Requires-Dist: scipy
Dynamic: author
Dynamic: author-email
Dynamic: classifier
Dynamic: description
Dynamic: description-content-type
Dynamic: home-page
Dynamic: license-file
Dynamic: project-url
Dynamic: requires-dist
Dynamic: requires-python
Dynamic: summary
